generate_docs/__init__.py
generate_docs/generator.py
generate_docs/how_to.py
generate_docs/readme.py
generate_docs/wiki.py
generate_docs-2.6.1.dist-info/LICENSE
generate_docs-2.6.1.dist-info/METADATA
generate_docs-2.6.1.dist-info/WHEEL
generate_docs-2.6.1.dist-info/entry_points.txt
generate_docs-2.6.1.dist-info/top_level.txt
generate_docs-2.6.1.dist-info/RECORD
