Metadata-Version: 2.1
Name: generate-docs
Version: 2.6.1
Summary: A docs generation package for the Sample Programs repo
Home-page: https://github.com/TheRenegadeCoder/sample-programs-docs-generator
Author: The Renegade Coder
Author-email: jeremy.grifski@therenegadecoder.com
License: UNKNOWN
Platform: UNKNOWN
Classifier: Programming Language :: Python :: 3
Classifier: License :: OSI Approved :: GNU General Public License v3 (GPLv3)
Classifier: Operating System :: OS Independent
Requires-Dist: feedparser (~=6.0.6)
Requires-Dist: beautifulsoup4 (~=4.9.3)
Requires-Dist: requests (~=2.25.1)
Requires-Dist: SnakeMD (~=0.7.0)
Requires-Dist: subete (~=0.5.1)
